django_salmonella-1.2.1.dist-info/METADATA
django_salmonella-1.2.1.dist-info/RECORD
django_salmonella-1.2.1.dist-info/WHEEL
django_salmonella-1.2.1.dist-info/top_level.txt
dynamic_raw_id/__init__.py
dynamic_raw_id/admin.py
dynamic_raw_id/filters.py
dynamic_raw_id/models.py
dynamic_raw_id/urls.py
dynamic_raw_id/views.py
dynamic_raw_id/widgets.py
dynamic_raw_id/static/dynamic_raw_id/img/icon-clear.gif
dynamic_raw_id/static/dynamic_raw_id/img/icon-lookup.gif
dynamic_raw_id/static/dynamic_raw_id/js/dynamic_raw_id.js
dynamic_raw_id/templates/dynamic_raw_id/label.html
dynamic_raw_id/templates/dynamic_raw_id/multi_label.html
dynamic_raw_id/templates/dynamic_raw_id/admin/filters/dynamic_raw_id_filter.html
dynamic_raw_id/templates/dynamic_raw_id/admin/widgets/dynamic_raw_id_field.html
dynamic_raw_id/templates/dynamic_raw_id/admin/widgets/dynamic_raw_id_field_dj111.html
dynamic_raw_id/tests/__init__.py
dynamic_raw_id/tests/test_integrity.py
dynamic_raw_id/tests/test_selenium.py
dynamic_raw_id/tests/testapp/__init__.py
dynamic_raw_id/tests/testapp/admin.py
dynamic_raw_id/tests/testapp/models.py
dynamic_raw_id/tests/testapp/settings.py
dynamic_raw_id/tests/testapp/urls.py
dynamic_raw_id/tests/testapp/migrations/0001_initial.py
dynamic_raw_id/tests/testapp/migrations/__init__.py
salmonella/__init__.py
salmonella/admin.py
salmonella/filters.py
salmonella/models.py
salmonella/urls.py
salmonella/views.py
salmonella/widgets.py
salmonella/static/salmonella/img/icon_deletelink.gif
salmonella/static/salmonella/img/selector-search.gif
salmonella/static/salmonella/js/salmonella.js
salmonella/templates/salmonella/label.html
salmonella/templates/salmonella/multi_label.html
salmonella/templates/salmonella/admin/filters/salmonella_filter.html
salmonella/templates/salmonella/admin/widgets/salmonella_field.html
salmonella/templates/salmonella/admin/widgets/salmonella_field_dj111.html
salmonella/tests/__init__.py
salmonella/tests/test_integrity.py
salmonella/tests/testapp/__init__.py
salmonella/tests/testapp/admin.py
salmonella/tests/testapp/models.py
salmonella/tests/testapp/settings.py
