Metadata-Version: 1.1
Name: django-salmonella
Version: 1.2.1
Summary: django-salmonella was renamed to django-dynamic-raw-id! raw_id_fields widget replacement that handles display of an object's string value on change and can be overridden via a template.
Home-page: https://pypi.org/project/django-dynamic-raw-id/
Author: Lincoln Loop: Seth Buntin, Yann Malet
Author-email: info@lincolnloop.com
License: UNKNOWN
Platform: UNKNOWN
Classifier: Development Status :: 5 - Production/Stable
Classifier: Environment :: Web Environment
Classifier: Intended Audience :: Developers
Classifier: License :: OSI Approved :: MIT License
Classifier: Operating System :: OS Independent
Classifier: Programming Language :: Python :: 2
Classifier: Programming Language :: Python :: 3
Classifier: Framework :: Django
